{
  "1": {
    "「<pc>さん。": "「<pc>さん。"
  },
  "2": {
    "「あなたも　グランゼドーラ王国へ行くのですね？": "「あなたも　グランゼドーラ王国へ行くのですね？"
  },
  "3": {
    "「……ふふっ。すみません。|　そんなに警戒しないでください。": "「……ふふっ。すみません。|　そんなに警戒しないでください。"
  },
  "4": {
    "「あなたは　ご存知ないかもしれませんが……": "「あなたは　ご存知ないかもしれませんが……"
  },
  "5": {
    "「<pc>さん。あなたの名前は|　意外に　知れ渡っているのですよ？|　あの冥王ネルゲルを……　倒した人物としてね。": "「<pc>さん。あなたの名前は|　意外に　知れ渡っているのですよ？|　あの冥王ネルゲルを……　倒した人物としてね。"
  },
  "6": {
    "「私の名前は　クロウズ。|　ある人を探し求めて|　世界中を　旅している者です。": "「私の名前は　クロウズ。|　ある人を探し求めて|　世界中を　旅している者です。"
  },
  "7": {
    "「操舵室へ　行くところだったのでしょう？|　私も　ご一緒させていただきますね。": "「操舵室へ　行くところだったのでしょう？|　私も　ご一緒させていただきますね。"
  },
  "8": {
    "「ダドリー副船長！|　やはり　どこにも見当たりません！": "「ダドリー副船長！|　やはり　どこにも見当たりません！"
  },
  "9": {
    "「なんということだ……。|　私たちの命づなである　魔法の羅針盤が|　消えてしまっただなんて……。": "「なんということだ……。|　私たちの命づなである　魔法の羅針盤が|　消えてしまっただなんて……。"
  },
  "10": {
    "「お　お客さま！": "「お　お客さま！"
  },
  "11": {
    "「申し訳ございません。|　ただいま　取り込み中でございまして……。": "「申し訳ございません。|　ただいま　取り込み中でございまして……。"
  },
  "12": {
    "「魔法の羅針盤が　なくなったのですね。": "「魔法の羅針盤が　なくなったのですね。"
  },
  "13": {
    "「い　いえ……　あの　その……。": "「い　いえ……　あの　その……。"
  },
  "14": {
    "「騒ぎは　外まで　聞こえていましたよ。|　魔法の羅針盤がなくては　迷いの霧を越えられず|　レンダーシアには　行けないはずですよね？": "「騒ぎは　外まで　聞こえていましたよ。|　魔法の羅針盤がなくては　迷いの霧を越えられず|　レンダーシアには　行けないはずですよね？"
  },
  "15": {
    "「はい……。おっしゃる通りでございます。|　しかし　エイブラム船長を始め|　多くの船員たちが　探しておりますから……。": "「はい……。おっしゃる通りでございます。|　しかし　エイブラム船長を始め|　多くの船員たちが　探しておりますから……。"
  },
  "16": {
    "「私は　どうしても　レンダーシアに|　行かなくてはならないのです。|　……なんとか　しなくては。": "「私は　どうしても　レンダーシアに|　行かなくてはならないのです。|　……なんとか　しなくては。"
  },
  "17": {
    "「エイブラム船長！　魔法の羅針盤は……？": "「エイブラム船長！　魔法の羅針盤は……？"
  },
  "18": {
    "「残念だが　わしの方は　収穫なしだ。|　その様子では　そちらも　ダメか。": "「残念だが　わしの方は　収穫なしだ。|　その様子では　そちらも　ダメか。"
  },
  "19": {
    "「……む？　キミは？": "「……む？　キミは？"
  },
  "20": {
    "「ちょっと　失礼。": "「ちょっと　失礼。"
  },
  "21": {
    "「な…………？": "「な…………？"
  },
  "22": {
    "「おお　そうだ！　わしとしたことが|　こんな大事なことを　忘れておったとは！": "「おお　そうだ！　わしとしたことが|　こんな大事なことを　忘れておったとは！"
  },
  "23": {
    "「こんなこともあろうかと　魔法の羅針盤は|　私が　ニセモノと　すり替えておいたのだった。": "「こんなこともあろうかと　魔法の羅針盤は|　私が　ニセモノと　すり替えておいたのだった。"
  },
  "24": {
    "「なくなったのは　ニセの羅針盤……|　本物の　魔法の羅針盤は　無事だ。|　騒がせて　申し訳ない。": "「なくなったのは　ニセの羅針盤……|　本物の　魔法の羅針盤は　無事だ。|　騒がせて　申し訳ない。"
  },
  "25": {
    "「そんな……！？": "「そんな……！？"
  },
  "26": {
    "「本船は　問題なく　レンダーシアに到着できる。|　さあ　みんな　持ち場へ戻れ！": "「本船は　問題なく　レンダーシアに到着できる。|　さあ　みんな　持ち場へ戻れ！"
  },
  "27": {
    "「……くっ！": "「……くっ！"
  },
  "28": {
    "「ニセの羅針盤があったとは　知りませんでした。|　まったく　船長も　お人が悪い。": "「ニセの羅針盤があったとは　知りませんでした。|　まったく　船長も　お人が悪い。"
  },
  "29": {
    "「……どうした　ダドリー？|　魔法の羅針盤の捜索は　どうなっている？": "「……どうした　ダドリー？|　魔法の羅針盤の捜索は　どうなっている？"
  },
  "30": {
    "「えっ？　今　船長が|　なくなったのは　ニセの羅針盤で|　本物は　無事だと　おっしゃったのでは？": "「えっ？　今　船長が|　なくなったのは　ニセの羅針盤で|　本物は　無事だと　おっしゃったのでは？"
  },
  "31": {
    "「バカモノ！　なに　寝ぼけたことを言っとる！|　ニセの羅針盤など　聞いたこともないぞ！！": "「バカモノ！　なに　寝ぼけたことを言っとる！|　ニセの羅針盤など　聞いたこともないぞ！！"
  },
  "32": {
    "「そんなことより　もう一度　手分けして|　すみずみまで探すのだ！　急げ！！": "「そんなことより　もう一度　手分けして|　すみずみまで探すのだ！　急げ！！"
  },
  "33": {
    "「は　はいっ！！": "「は　はいっ！！"
  },
  "34": {
    "「船長には　すこし|　記憶違いを　していただきました。|　私は　こういう技を心得ているのです。": "「船長には　すこし|　記憶違いを　していただきました。|　私は　こういう技を心得ているのです。"
  },
  "35": {
    "「……それより　最初に　操舵室から出ていった|　赤い髪の船員を　覚えていますね？|　彼を　追ってください。": "「……それより　最初に　操舵室から出ていった|　赤い髪の船員を　覚えていますね？|　彼を　追ってください。"
  },
  "36": {
    "「お客さま　申し訳ございません。|　先ほどは　たいへん見苦しいところを|　お見せいたしました。": "「お客さま　申し訳ございません。|　先ほどは　たいへん見苦しいところを|　お見せいたしました。"
  },
  "37": {
    "「本船は　まもなく　迷いの霧が見える海域まで|　近づいておりますが……　残念ながら|　魔法の羅針盤は　まだ　見つかっておりません。": "「本船は　まもなく　迷いの霧が見える海域まで|　近づいておりますが……　残念ながら|　魔法の羅針盤は　まだ　見つかっておりません。"
  },
  "38": {
    "「この操舵室には　誰でも入れる状態でしたが|　常にクルーが　ふたり以上　おりましたし|　怪しい者がいたという報告も　ありません。": "「この操舵室には　誰でも入れる状態でしたが|　常にクルーが　ふたり以上　おりましたし|　怪しい者がいたという報告も　ありません。"
  },
  "39": {
    "「ふと見たら　魔法の羅針盤が|　煙のように　消えていたのでございます。|　いったい　何が起こったのか　サッパリで……。": "「ふと見たら　魔法の羅針盤が|　煙のように　消えていたのでございます。|　いったい　何が起こったのか　サッパリで……。"
  },
  "40": {
    "「しかし　このままでは　レンドア島に|　戻らなくてはいけません。|　なんとしても　探しださなくては！": "「しかし　このままでは　レンドア島に|　戻らなくてはいけません。|　なんとしても　探しださなくては！"
  },
  "41": {
    "「……これが　ニセモノだと？|　まさか　そんなはずが……。": "「……これが　ニセモノだと？|　まさか　そんなはずが……。"
  },
  "42": {
    "「先に着いているとは　さすがですね。|　<pc>さん。": "「先に着いているとは　さすがですね。|　<pc>さん。"
  },
  "43": {
    "「お…お前ら……　見やがったな！？": "「お…お前ら……　見やがったな！？"
  },
  "44": {
    "「ニセの羅針盤を　つかまされるとは|　このオレも　ヤキが　回ったもんだぜ。": "「ニセの羅針盤を　つかまされるとは|　このオレも　ヤキが　回ったもんだぜ。"
  },
  "45": {
    "「いいえ。ニセの羅針盤なんて|　最初から　存在しませんよ。": "「いいえ。ニセの羅針盤なんて|　最初から　存在しませんよ。"
  },
  "46": {
    "「え？　ええ？": "「え？　ええ？"
  },
  "47": {
    "「……私たちは　どうしても|　レンダーシアに　渡らなくてはならないのです。": "「……私たちは　どうしても|　レンダーシアに　渡らなくてはならないのです。"
  },
  "48": {
    "「その　本物の羅針盤を　返してもらいますよ。": "「その　本物の羅針盤を　返してもらいますよ。"
  },
  "49": {
    "「くっそおぉおおぉぉおおおおおおっ！！|　よくも　だましやがったな！！": "「くっそおぉおおぉぉおおおおおおっ！！|　よくも　だましやがったな！！"
  },
  "50": {
    "「絶対　レンダーシアには　行かせねえええ！！|　魔法の羅針盤なんか　こうしてやるっ！！": "「絶対　レンダーシアには　行かせねえええ！！|　魔法の羅針盤なんか　こうしてやるっ！！"
  },
  "51": {
    "「捨てても　無駄です。": "「捨てても　無駄です。"
  },
  "52": {
    "「たとえ　海の底に沈めたとしても|　私が　たやすく　見つけだしてみせましょう。": "「たとえ　海の底に沈めたとしても|　私が　たやすく　見つけだしてみせましょう。"
  },
  "53": {
    "「くっ……！|　どこまでも　こしゃくな！！": "「くっ……！|　どこまでも　こしゃくな！！"
  },
  "54": {
    "「………………。": "「………………。"
  },
  "55": {
    "「コトを荒立てるなと　言われていたが|　……こうなったら　仕方がない。": "「コトを荒立てるなと　言われていたが|　……こうなったら　仕方がない。"
  },
  "56": {
    "「オレは　冥王ネルゲルさまの使い　マボック！": "「オレは　冥王ネルゲルさまの使い　マボック！"
  },
  "57": {
    "「冥王さまの　ご遺命により|　何者にも　レンダーシアの地は　踏ません！！": "「冥王さまの　ご遺命により|　何者にも　レンダーシアの地は　踏ません！！"
  },
  "58": {
    "「……私は　急いでいるのです。": "「……私は　急いでいるのです。"
  },
  "59": {
    "「ぐ……　ぁ…………。": "「ぐ……　ぁ…………。"
  },
  "60": {
    "「死して後も　冥王ネルゲルは|　レンダーシアの地へ渡る者を　妨害するよう|　配下に　命じていたのですね……。": "「死して後も　冥王ネルゲルは|　レンダーシアの地へ渡る者を　妨害するよう|　配下に　命じていたのですね……。"
  },
  "61": {
    "「いったい　なんの騒ぎだ！？": "「いったい　なんの騒ぎだ！？"
  },
  "62": {
    "「ま　ま　ま　魔物がっ！": "「ま　ま　ま　魔物がっ！"
  },
  "63": {
    "「レ…レンダーシアの地を……　踏む者に|　災い……　あ　れ…………！": "「レ…レンダーシアの地を……　踏む者に|　災い……　あ　れ…………！"
  },
  "64": {
    "「よかった。海に　捨てられなくて。|　危うく　<pc>さんに|　海へ　飛び込んでもらうところでしたよ。": "「よかった。海に　捨てられなくて。|　危うく　<pc>さんに|　海へ　飛び込んでもらうところでしたよ。"
  },
  "65": {
    "「我々が求め　探し続けていた　魔法の羅針盤が|　ついに　この手に戻った……。": "「我々が求め　探し続けていた　魔法の羅針盤が|　ついに　この手に戻った……。"
  },
  "66": {
    "「諸君の協力に　感謝する！|　まもなく　本船は　迷いの霧に突入する。|　キミたちも　船内で安全を確保してくれたまえ！": "「諸君の協力に　感謝する！|　まもなく　本船は　迷いの霧に突入する。|　キミたちも　船内で安全を確保してくれたまえ！"
  },
  "67": {
    "「これで　レンダーシアに行けるはず……|　とはいえ　到着するまでには|　まだ　しばらく時間が　かかるでしょう。": "「これで　レンダーシアに行けるはず……|　とはいえ　到着するまでには|　まだ　しばらく時間が　かかるでしょう。"
  },
  "68": {
    "「もし　船内で　することがなくなったら|　客室案内係に言えば　港に着くまで|　部屋で　休ませてもらえますよ。": "「もし　船内で　することがなくなったら|　客室案内係に言えば　港に着くまで|　部屋で　休ませてもらえますよ。"
  },
  "69": {
    "「１階の　カウンターにいる人です。|　覚えておいてくださいね。": "「１階の　カウンターにいる人です。|　覚えておいてくださいね。"
  },
  "70": {
    "「<pc>さん。": "「<pc>さん。"
  },
  "71": {
    "「あなたも　これから|　お休みになるところでしたか。": "「あなたも　これから|　お休みになるところでしたか。"
  },
  "72": {
    "「ご乗船の　お客さまに申し上げます。": "「ご乗船の　お客さまに申し上げます。"
  },
  "73": {
    "「これより　本船は　迷いの霧に突入いたします。|　甲板や　デッキにいらっしゃる　お客さまは|　速やかに　船内へ　お戻りくださいませ。": "「これより　本船は　迷いの霧に突入いたします。|　甲板や　デッキにいらっしゃる　お客さまは|　速やかに　船内へ　お戻りくださいませ。"
  },
  "74": {
    "「ダメですっ！|　計器が……　すべて　作動しません！！": "「ダメですっ！|　計器が……　すべて　作動しません！！"
  },
  "75": {
    "「こちらもです！|　まったく　舵が　ききません！！": "「こちらもです！|　まったく　舵が　ききません！！"
  },
  "76": {
    "「これが……　迷いの霧のチカラか。": "「これが……　迷いの霧のチカラか。"
  },
  "77": {
    "「頼むぞ。|　英知の結晶……　魔法の羅針盤よ！": "「頼むぞ。|　英知の結晶……　魔法の羅針盤よ！"
  },
  "78": {
    "「だ……　ダメか…………。": "「だ……　ダメか…………。"
  },
  "79": {
    "「せ…船長！|　舵が！　舵が　ききます！！": "「せ…船長！|　舵が！　舵が　ききます！！"
  },
  "80": {
    "「よし！|　あの光が指し示す方向に　進路を取れ！！": "「よし！|　あの光が指し示す方向に　進路を取れ！！"
  },
  "81": {
    "「……どうやら　落ち着いたようですね。": "「……どうやら　落ち着いたようですね。"
  },
  "82": {
    "「後のことは　船員たちに　まかせて|　私たちは　休ませてもらうことにしましょう。": "「後のことは　船員たちに　まかせて|　私たちは　休ませてもらうことにしましょう。"
  },
  "83": {
    "「なぜだ……？": "「なぜだ……？"
  },
  "84": {
    "「迷いの霧は　無事　抜けましたが……|　潮の流れが強く　グランゼドーラの海域には|　どうやっても　近づけないようです。": "「迷いの霧は　無事　抜けましたが……|　潮の流れが強く　グランゼドーラの海域には|　どうやっても　近づけないようです。"
  },
  "85": {
    "「仕方あるまい。|　今は　レンダーシアへの上陸が　最優先だ。": "「仕方あるまい。|　今は　レンダーシアへの上陸が　最優先だ。"
  },
  "86": {
    "「本船は　ここに停泊する！|　不本意ではあるが　乗客には　陸路で|　グランゼドーラ王国へ　向かってもらおう。": "「本船は　ここに停泊する！|　不本意ではあるが　乗客には　陸路で|　グランゼドーラ王国へ　向かってもらおう。"
  },
  "87": {
    "「お客さまに　ご案内申し上げます。|　本船は　レンダーシアに　到着いたしました。": "「お客さまに　ご案内申し上げます。|　本船は　レンダーシアに　到着いたしました。"
  },
  "88": {
    "「目的地である　グランゼドーラ王国の港とは|　異なる場所となりましたが　レンダーシア上陸を|　最優先と判断し　停泊いたします。": "「目的地である　グランゼドーラ王国の港とは|　異なる場所となりましたが　レンダーシア上陸を|　最優先と判断し　停泊いたします。"
  },
  "89": {
    "「現在　クルーたちが|　お客さまを　浜辺まで　お送りしております。": "「現在　クルーたちが|　お客さまを　浜辺まで　お送りしております。"
  },
  "90": {
    "「グランゼドーラ王国を目指される　お客さまは|　陸路にて　お向かいください。": "「グランゼドーラ王国を目指される　お客さまは|　陸路にて　お向かいください。"
  },
  "91": {
    "「なお　レンドア島へのお戻りを|　ご希望なされる　お客さまは|　浜辺にいるクルーに　お申し付けください。": "「なお　レンドア島へのお戻りを|　ご希望なされる　お客さまは|　浜辺にいるクルーに　お申し付けください。"
  },
  "92": {
    "「なぜ　グランゼドーラ王国に　着けん……。": "「なぜ　グランゼドーラ王国に　着けん……。"
  },
  "93": {
    "「おそらく　１階のデッキに向かったはず……。|　私も　すぐに向かいます。": "「おそらく　１階のデッキに向かったはず……。|　私も　すぐに向かいます。"
  }
}