{
  "93050": {
    "「おお　我がドルワームの恩人　<pc>よ！\n　待っておったぞ。ささ　こちらに。": "「おお　我がドルワームの恩人　<pc>よ！\n　待っておったぞ。ささ　こちらに。"
  },
  "93051": {
    "「ヴェリナード王国での　そなたの活躍は\n　こちらにも　届いておる。\n　見事な　はたらきだったそうじゃな。": "「ヴェリナード王国での　そなたの活躍は\n　こちらにも　届いておる。\n　見事な　はたらきだったそうじゃな。"
  },
  "93052": {
    "「ヴェリナードに現れた　王族を狙う不審な男が \n　ドルワームに　潜伏していることも聞いた。\n　王子であるラミザは　騎士団が守っているが……": "「ヴェリナードに現れた　王族を狙う不審な男が \n　ドルワームに　潜伏していることも聞いた。\n　王子であるラミザは　騎士団が守っているが……"
  },
  "93053": {
    "「そなたには　もうひとりの王家の血を引く者……\n　チリの護衛を　お願いしたいのじゃ。\n　どうじゃ？　引き受けてくれるか？<yesno><close>": "「そなたには　もうひとりの王家の血を引く者……\n　チリの護衛を　お願いしたいのじゃ。\n　どうじゃ？　引き受けてくれるか？<yesno><close>"
  },
  "93054": {
    "「そんなこと　言うなんてつれないのね。\n　私からもお願い！　ねっ　<pc>！？": "「そんなこと　言うなんてつれないのね。\n　私からもお願い！　ねっ　<pc>！？"
  },
  "93055": {
    "「……どうじゃ？\n　チリの護衛　引き受けてくれんか？<yesno><close>": "「……どうじゃ？\n　チリの護衛　引き受けてくれんか？<yesno><close>"
  },
  "93056": {
    "「うむ。礼を言うぞ　<pc>。\n　くれぐれも　よろしく頼む。": "「うむ。礼を言うぞ　<pc>。\n　くれぐれも　よろしく頼む。"
  },
  "93057": {
    "「ありがとう　<pc>。\n　迷惑かけちゃうけど……\n　しばらくの間　どうか　よろしくね。": "「ありがとう　<pc>。\n　迷惑かけちゃうけど……\n　しばらくの間　どうか　よろしくね。"
  },
  "93058": {
    "「ときに　ドゥラよ。\n　護衛を厳重にする以外の対策は\n　何か　みつかったのか？": "「ときに　ドゥラよ。\n　護衛を厳重にする以外の対策は\n　何か　みつかったのか？"
  },
  "93059": {
    "「その件なのですが……。": "「その件なのですが……。"
  },
  "93060": {
    "「なんじゃ？\n　お前にしては　珍しく弱気な顔ではないか。\n　申してみよ。": "「なんじゃ？\n　お前にしては　珍しく弱気な顔ではないか。\n　申してみよ。"
  },
  "93061": {
    "「……我が研究院で　探知機を作成しました。\n　探知機と対になった発信機を　身につけることで\n　その人物の動向を　追うことができるものです。": "「……我が研究院で　探知機を作成しました。\n　探知機と対になった発信機を　身につけることで\n　その人物の動向を　追うことができるものです。"
  },
  "93062": {
    "「これで　万が一　ラミザ王子らの身に\n　何かあっても　行方を追跡することができます。": "「これで　万が一　ラミザ王子らの身に\n　何かあっても　行方を追跡することができます。"
  },
  "93063": {
    "「すごいや！　さすが　ドゥラくんだ！\n　うんうん。護衛と探知機……\n　これで　バッチリだね！": "「すごいや！　さすが　ドゥラくんだ！\n　うんうん。護衛と探知機……\n　これで　バッチリだね！"
  },
  "93064": {
    "「……探知機は　完成したのです。 \n　しかし　肝心の発信機の出力が弱く\n　近距離までしか　追跡することができません。": "「……探知機は　完成したのです。 \n　しかし　肝心の発信機の出力が弱く\n　近距離までしか　追跡することができません。"
  },
  "93065": {
    "「遠方まで　追跡可能にするためには\n　ガテリア式真空管という　古代ガテリアに伝わる\n　特殊な部品が　必要なのですが……": "「遠方まで　追跡可能にするためには\n　ガテリア式真空管という　古代ガテリアに伝わる\n　特殊な部品が　必要なのですが……"
  },
  "93066": {
    "「現代では　入手が極めて困難なのです。\n　このままでは　せっかくの探知機も\n　充分な効果を　見込めないでしょう……。": "「現代では　入手が極めて困難なのです。\n　このままでは　せっかくの探知機も\n　充分な効果を　見込めないでしょう……。"
  },
  "93067": {
    "「そ　そんな……！\n　名案だと思ったのに……。": "「そ　そんな……！\n　名案だと思ったのに……。"
  },
  "93068": {
    "「ガテリア式真空管……\n　……知ってる。それなら　前に\n　お父さんのガラクタの中で　見たことがあるわ。": "「ガテリア式真空管……\n　……知ってる。それなら　前に\n　お父さんのガラクタの中で　見たことがあるわ。"
  },
  "93069": {
    "「それは本当ですか　チリ王女！？": "「それは本当ですか　チリ王女！？"
  },
  "93070": {
    "「ドゥラ院長。\n　王女はやめてと　何度も言ったでしょう？": "「ドゥラ院長。\n　王女はやめてと　何度も言ったでしょう？"
  },
  "93071": {
    "「何度言われても　チリ様は王女。\n　それは　変わりありません。": "「何度言われても　チリ様は王女。\n　それは　変わりありません。"
  },
  "93072": {
    "「……そんなことより\n　ガテリア式真空管の持ち主というのは\n　チリ王女を　育ててくれた方のことですか？": "「……そんなことより\n　ガテリア式真空管の持ち主というのは\n　チリ王女を　育ててくれた方のことですか？"
  },
  "93073": {
    "「ええ。父は　岳都ガタラに住んでいます。\n　ガラクタが大好きで　いつも\n　珍しいものばかり　集めて過ごしているのよ。": "「ええ。父は　岳都ガタラに住んでいます。\n　ガラクタが大好きで　いつも\n　珍しいものばかり　集めて過ごしているのよ。"
  },
  "93074": {
    "「では　さっそく\n　その方の所まで向かう準備を……。": "「では　さっそく\n　その方の所まで向かう準備を……。"
  },
  "93075": {
    "「待って！": "「待って！"
  },
  "93076": {
    "「あの　お父さんのことだもの。\n　自分の宝物を　そう簡単に渡すわけない。\n　だから……　私も行くわ！": "「あの　お父さんのことだもの。\n　自分の宝物を　そう簡単に渡すわけない。\n　だから……　私も行くわ！"
  },
  "93077": {
    "「いいですよね　国王様？\n　父は　なんというか……　たいへんな変わり者で\n　きっと　説得は　私にしかできません！": "「いいですよね　国王様？\n　父は　なんというか……　たいへんな変わり者で\n　きっと　説得は　私にしかできません！"
  },
  "93078": {
    "「ご自分の立場を　わかっているのですか！？\n　道中　何者かに狙われでもしたら……": "「ご自分の立場を　わかっているのですか！？\n　道中　何者かに狙われでもしたら……"
  },
  "93079": {
    "「そのための　<pc>の護衛なんでしょう？ \n　ドルワームの英雄　<pc>に\n　ガタラまで同行してもらえば　大丈夫よ！": "「そのための　<pc>の護衛なんでしょう？ \n　ドルワームの英雄　<pc>に\n　ガタラまで同行してもらえば　大丈夫よ！"
  },
  "93080": {
    "「……やむを得んだろう。\n　ただし！　現状で目立つのは　避けたい。\n　この任務は　少人数での隠密行動とする。": "「……やむを得んだろう。\n　ただし！　現状で目立つのは　避けたい。\n　この任務は　少人数での隠密行動とする。"
  },
  "93081": {
    "「チリの養父のもとへ向かうのは\n　チリとドゥラ　そして<pc>のみじゃ。\n　それで　よいな？": "「チリの養父のもとへ向かうのは\n　チリとドゥラ　そして<pc>のみじゃ。\n　それで　よいな？"
  },
  "93082": {
    "「ありがとうございます　国王様。\n　必ず　ガテリア式真空管を持ちかえってきます。": "「ありがとうございます　国王様。\n　必ず　ガテリア式真空管を持ちかえってきます。"
  },
  "93083": {
    "「うう……　こんな時にボクだけ\n　何もできないなんて　申し訳ないけど……。\n　皆　くれぐれも　道中気をつけてね。": "「うう……　こんな時にボクだけ\n　何もできないなんて　申し訳ないけど……。\n　皆　くれぐれも　道中気をつけてね。"
  },
  "93084": {
    "「それじゃ　よろしくね　<pc>！\n　<pc>が　先導してくれたら\n　私たちも　後を追いかけていくわ。": "「それじゃ　よろしくね　<pc>！\n　<pc>が　先導してくれたら\n　私たちも　後を追いかけていくわ。"
  },
  "93085": {
    "「３人で　お父さんのいる　岳都ガタラへ\n　向かいましょう！": "「３人で　お父さんのいる　岳都ガタラへ\n　向かいましょう！"
  },
  "93086": {
    "「あっ！　元ポツコン２号さんじゃないですか！\n　それに　チリさんまで！！\n　おひさしぶりです　チリさん……<heart>": "「あっ！　元ポツコン２号さんじゃないですか！\n　それに　チリさんまで！！\n　おひさしぶりです　チリさん……<heart>"
  },
  "93087": {
    "「ひさしぶりだね　ポツコン。\n　お父さんはいる？": "「ひさしぶりだね　ポツコン。\n　お父さんはいる？"
  },
  "93088": {
    "「はいっ！　あちらに。": "「はいっ！　あちらに。"
  },
  "93089": {
    "「ダストンさま　ダストンさま～！\n　チリさんが　いらしてますよ。": "「ダストンさま　ダストンさま～！\n　チリさんが　いらしてますよ。"
  },
  "93090": {
    "「……チリ！？": "「……チリ！？"
  },
  "93091": {
    "「むきゃーー！！　もきぃーーー！！\n　アンタってヤツは　まったく\n　あぎゃぎゃっな娘ですねッ！": "「むきゃーー！！　もきぃーーー！！\n　アンタってヤツは　まったく\n　あぎゃぎゃっな娘ですねッ！"
  },
  "93092": {
    "「ああ　ごめん　ごめん。\n　しばらく　顔も出さずにいて。": "「ああ　ごめん　ごめん。\n　しばらく　顔も出さずにいて。"
  },
  "93094": {
    "「むきゃっ？": "「むきゃっ？"
  },
  "93095": {
    "「え？　今　なんて言いました……？\n　チリ……　王女……？": "「え？　今　なんて言いました……？\n　チリ……　王女……？"
  },
  "93096": {
    "「えええええええっ！？ \n　まさか　チリさんの本当の親って……\n　ドルワームの王様だったんですかぁ！？": "「えええええええっ！？ \n　まさか　チリさんの本当の親って……\n　ドルワームの王様だったんですかぁ！？"
  },
  "93097": {
    "「へー　アンタ　王女だったんですか。\n　王女なのに　捨てられちまうなんて\n　よっぽどの役立たずだったんですねえ。": "「へー　アンタ　王女だったんですか。\n　王女なのに　捨てられちまうなんて\n　よっぽどの役立たずだったんですねえ。"
  },
  "93098": {
    "「チリさんと一緒にいる　身なりのキレイな\n　いかにも優秀そうな男……。\n　ま…まさか　チリさんは　恋人を紹介に……！？": "「チリさんと一緒にいる　身なりのキレイな\n　いかにも優秀そうな男……。\n　ま…まさか　チリさんは　恋人を紹介に……！？"
  },
  "93099": {
    "「はじめまして。ドルワーム王立研究院で \n　院長をつとめている　ドゥラと申します。\n　今日は　ダストン氏に用があって参りました。": "「はじめまして。ドルワーム王立研究院で \n　院長をつとめている　ドゥラと申します。\n　今日は　ダストン氏に用があって参りました。"
  },
  "93100": {
    "「あぎゃばっ！　い…院長……？\n　わしは　そんな優秀そうなヤツは苦手ですよッ！": "「あぎゃばっ！　い…院長……？\n　わしは　そんな優秀そうなヤツは苦手ですよッ！"
  },
  "93101": {
    "「ごめんなさい。父に　悪気はないんです。\n　どうか　気を悪くしないでください。": "「ごめんなさい。父に　悪気はないんです。\n　どうか　気を悪くしないでください。"
  },
  "93102": {
    "「あのね　お父さん。今　アストルティア中の \n　王族が狙われるという事件が　発生してるの。\n　相手の正体や目的は　わからないんだけど……": "「あのね　お父さん。今　アストルティア中の \n　王族が狙われるという事件が　発生してるの。\n　相手の正体や目的は　わからないんだけど……"
  },
  "93103": {
    "「ドゥラ院長は　私やラミザ王子がさらわれても\n　すぐに　居場所がわかっちゃう\n　すごい発信機を　作ってくれてるんだ。": "「ドゥラ院長は　私やラミザ王子がさらわれても\n　すぐに　居場所がわかっちゃう\n　すごい発信機を　作ってくれてるんだ。"
  },
  "93104": {
    "「ただ……そのためには　ガテリア式真空管という\n　古代の部品が必要なんです。あなたが　それを\n　お持ちだと聞いて　協力いただけないかと。": "「ただ……そのためには　ガテリア式真空管という\n　古代の部品が必要なんです。あなたが　それを\n　お持ちだと聞いて　協力いただけないかと。"
  },
  "93105": {
    "「ガテリア式真空管……？\n　そんなもの　知らねえですよッ？": "「ガテリア式真空管……？\n　そんなもの　知らねえですよッ？"
  },
  "93106": {
    "「ああ　ほら！　ダストンさま……！\n　前に　ここを訪れた考古学者が\n　すごく貴重だって　言ってた……": "「ああ　ほら！　ダストンさま……！\n　前に　ここを訪れた考古学者が\n　すごく貴重だって　言ってた……"
  },
  "93107": {
    "「ああ！　そんなもの　もう　とっくに\n　カルデア洞穴の　ふかーい所に\n　捨てちまいましたよッ！": "「ああ！　そんなもの　もう　とっくに\n　カルデア洞穴の　ふかーい所に\n　捨てちまいましたよッ！"
  },
  "93108": {
    "「な…なんだって……！？\n　あんな貴重なものを……。": "「な…なんだって……！？\n　あんな貴重なものを……。"
  },
  "93109": {
    "「大丈夫！　あきらめるには　まだ早いわ！\n　私に　考えがあるの。": "「大丈夫！　あきらめるには　まだ早いわ！\n　私に　考えがあるの。"
  },
  "93110": {
    "「ねえ　お父さん。\n　それを　捨てた場所まで行って\n　もう一度　ここに持ってきてくれないかな？": "「ねえ　お父さん。\n　それを　捨てた場所まで行って\n　もう一度　ここに持ってきてくれないかな？"
  },
  "93111": {
    "「な…なんで　わしが！ \n　そんなことするわけねえですよッ！\n　あんな貴重な物　もう見たくねえんですから！": "「な…なんで　わしが！ \n　そんなことするわけねえですよッ！\n　あんな貴重な物　もう見たくねえんですから！"
  },
  "93112": {
    "「じつは　私ね。お父さんが喜びそうなガラクタを\n　たくさん集めて　ドルワームに保管してるの。\n　やってくれるなら　それを好きなだけあげるわ！": "「じつは　私ね。お父さんが喜びそうなガラクタを\n　たくさん集めて　ドルワームに保管してるの。\n　やってくれるなら　それを好きなだけあげるわ！"
  },
  "93113": {
    "「ぐぬぬぬぬぬ……。": "「ぐぬぬぬぬぬ……。"
  },
  "93114": {
    "「決まり……　ねっ！": "「決まり……　ねっ！"
  },
  "93115": {
    "「しょ　しょうがねえですねッ！\n　言っておきますが　ガラクタのためであって\n　アンタのためじゃねえんですからねッ！": "「しょ　しょうがねえですねッ！\n　言っておきますが　ガラクタのためであって\n　アンタのためじゃねえんですからねッ！"
  },
  "93116": {
    "「うんうん　わかってる。\n　ありがとう　お父さん！": "「うんうん　わかってる。\n　ありがとう　お父さん！"
  },
  "93117": {
    "「そうと決まれば　ひとっ走り行ってくるですよ！\n　ここで　待ってやがるがいいですッ！": "「そうと決まれば　ひとっ走り行ってくるですよ！\n　ここで　待ってやがるがいいですッ！"
  },
  "93118": {
    "「とは言え……。あの　お父さんが寄り道せず \n　ちゃんと目的を果たせるか　心配だね。\n　私が　追いかけていきたいところだけど……": "「とは言え……。あの　お父さんが寄り道せず \n　ちゃんと目的を果たせるか　心配だね。\n　私が　追いかけていきたいところだけど……"
  },
  "93119": {
    "「ねえ　<pc>。\n　私の代わりに　お父さんの後をついていって\n　様子を　見てきてくれないかな？": "「ねえ　<pc>。\n　私の代わりに　お父さんの後をついていって\n　様子を　見てきてくれないかな？"
  },
  "93120": {
    "「チリ王女は　私が責任をもって守ります。\n　我々は　ここで待っていますので\n　そちらは　お願いしますね　<pc>さん。": "「チリ王女は　私が責任をもって守ります。\n　我々は　ここで待っていますので\n　そちらは　お願いしますね　<pc>さん。"
  },
  "93121": {
    "「お父さんが向かった　カルデア洞穴へは \n　ガタラを出て　北東に進むと　たどり着けるよ。\n　頼んだからね　<pc>！": "「お父さんが向かった　カルデア洞穴へは \n　ガタラを出て　北東に進むと　たどり着けるよ。\n　頼んだからね　<pc>！"
  },
  "93122": {
    "「ああっ　元ポツコン２号さん。\n　ダストンさまなら　カルデア洞穴へ\n　向かわれましたよ。": "「ああっ　元ポツコン２号さん。\n　ダストンさまなら　カルデア洞穴へ\n　向かわれましたよ。"
  },
  "93123": {
    "「高性能発信機を　完成させるためには\n　ダストン氏に　ガテリア式真空管を\n　持ちかえっていただかねば　なりません。": "「高性能発信機を　完成させるためには\n　ダストン氏に　ガテリア式真空管を\n　持ちかえっていただかねば　なりません。"
  },
  "93124": {
    "「とは言え……あの　お父さんが寄り道せず \n　ちゃんと　目的を果たせるか心配ね。\n　私が　追いかけていきたいところだけど……。": "「とは言え……あの　お父さんが寄り道せず \n　ちゃんと　目的を果たせるか心配ね。\n　私が　追いかけていきたいところだけど……。"
  },
  "93125": {
    "「ねえ　<pc>。\n　私の代わりに　お父さんの後をついていって\n　様子を　見てきてくれないかな？": "「ねえ　<pc>。\n　私の代わりに　お父さんの後をついていって\n　様子を　見てきてくれないかな？"
  },
  "93126": {
    "「お父さんが向かった　カルデア洞穴へは \n　ガタラを出て　北東に進むと　たどり着けるよ。\n　きっと　いちばん奥辺りにいるんじゃないかな？": "「お父さんが向かった　カルデア洞穴へは \n　ガタラを出て　北東に進むと　たどり着けるよ。\n　きっと　いちばん奥辺りにいるんじゃないかな？"
  },
  "93127": {
    "「チリ王女は　私が責任をもって守ります。\n　我々は　ここで待っていますので\n　そちらは　お願いしますね　<pc>さん。": "「チリ王女は　私が責任をもって守ります。\n　我々は　ここで待っていますので\n　そちらは　お願いしますね　<pc>さん。"
  },
  "93128": {
    "「どうやら　お父さんも　あなたのことは\n　気に入ってるみたいだしね。\n　頼んだよ　<pc>！": "「どうやら　お父さんも　あなたのことは\n　気に入ってるみたいだしね。\n　頼んだよ　<pc>！"
  },
  "93129": {
    "「たしか　この辺りから\n　ブン投げたんでしたっけ？": "「たしか　この辺りから\n　ブン投げたんでしたっけ？"
  },
  "93130": {
    "「おお　みつけたですよッ！\n　あんなところに　引っかかってるなんて\n　なかなかの　わからずやでごぜえますなッ。": "「おお　みつけたですよッ！\n　あんなところに　引っかかってるなんて\n　なかなかの　わからずやでごぜえますなッ。"
  },
  "93131": {
    "「おや　アンタも来たんですか？\n　こんな場所にまで　わざわざ来るなんて\n　よっぽどの　ヒマ人でいやがったんですねえ。": "「おや　アンタも来たんですか？\n　こんな場所にまで　わざわざ来るなんて\n　よっぽどの　ヒマ人でいやがったんですねえ。"
  },
  "93132": {
    "「まあ　そんなことはいいです。\n　せっかく　アンタも来たなら……": "「まあ　そんなことはいいです。\n　せっかく　アンタも来たなら……"
  },
  "93133": {
    "「わしが　今から　あぎゃぎゃってするので\n　アンタは　そこに　ただボーッと\n　つっ立ってるが　いいですッ！": "「わしが　今から　あぎゃぎゃってするので\n　アンタは　そこに　ただボーッと\n　つっ立ってるが　いいですッ！"
  },
  "93134": {
    "「よっこらせっと。": "「よっこらせっと。"
  },
  "93135": {
    "「こ…こんな役に立つもの \n　わしは　持ちたくねえんですッ！\n　これは　アンタに　預けますよッ！": "「こ…こんな役に立つもの \n　わしは　持ちたくねえんですッ！\n　これは　アンタに　預けますよッ！"
  },
  "93136": {
    "<pc>は\nガテリア式真空管（だいじなもの）を\n手に入れた！<me 60>": "<pc>は\nガテリア式真空管（だいじなもの）を\n手に入れた！<me 60>"
  },
  "93137": {
    "「ぐぎゃぎゃぎゃッ！\n　これで　ドルワームのガラクタは\n　ぜーんぶ　わしのものですッ！": "「ぐぎゃぎゃぎゃッ！\n　これで　ドルワームのガラクタは\n　ぜーんぶ　わしのものですッ！"
  },
  "93138": {
    "「そうと決まれば　こんな場所とは \n　一刻も早く　オサラバですよッ！": "「そうと決まれば　こんな場所とは \n　一刻も早く　オサラバですよッ！"
  },
  "93139": {
    "「おかえりなさい！\n　ダストンさま　元ポツコン２号さん。": "「おかえりなさい！\n　ダストンさま　元ポツコン２号さん。"
  },
  "93140": {
    "「ガテリア式真空管　持ちかえってくれたんだね。\n　ありがとう！！": "「ガテリア式真空管　持ちかえってくれたんだね。\n　ありがとう！！"
  },
  "93141": {
    "「ガラクタをくれるって約束…… \n　忘れてねえでしょうね？": "「ガラクタをくれるって約束…… \n　忘れてねえでしょうね？"
  },
  "93142": {
    "「うんうん　だいじょーぶだよっ！\n　抱えきれないほどの　ガラクタをあげるから\n　楽しみにしてて！": "「うんうん　だいじょーぶだよっ！\n　抱えきれないほどの　ガラクタをあげるから\n　楽しみにしてて！"
  },
  "93143": {
    "「せっかく　材料もそろったのですし\n　ここで　発信機を完成させましょう。\n　ガテリア式真空管を　こちらに。": "「せっかく　材料もそろったのですし\n　ここで　発信機を完成させましょう。\n　ガテリア式真空管を　こちらに。"
  },
  "93144": {
    "<pc>は　ドゥラ院長に\nガテリア式真空管を　渡した！": "<pc>は　ドゥラ院長に\nガテリア式真空管を　渡した！"
  },
  "93145": {
    "「すぐに　作業を開始できるよう\n　準備をしておいたんです。\n　完成まで　少々　お待ちください。": "「すぐに　作業を開始できるよう\n　準備をしておいたんです。\n　完成まで　少々　お待ちください。"
  },
  "93146": {
    "ドゥラ院長は　ガテリア式真空管を使って\nあっという間に　高性能発信機を　完成させた！": "ドゥラ院長は　ガテリア式真空管を使って\nあっという間に　高性能発信機を　完成させた！"
  },
  "93147": {
    "「これが　発信機……？\n　……きれい。": "「これが　発信機……？\n　……きれい。"
  },
  "93148": {
    "「感度は　良好。動作も問題ありません。 \n　成功です！　\n　これを　国王とラミザ王子にも届けねば！": "「感度は　良好。動作も問題ありません。 \n　成功です！　\n　これを　国王とラミザ王子にも届けねば！"
  },
  "93149": {
    "「我々は　ドルワームに戻ります。\n　お世話になりました。\n　こちらには　後日　必ず謝礼を届けさせます。": "「我々は　ドルワームに戻ります。\n　お世話になりました。\n　こちらには　後日　必ず謝礼を届けさせます。"
  },
  "93150": {
    "「……届ける？　何言ってやがるんですか？ \n　わしも　ドルワームへ行きますよッ！": "「……届ける？　何言ってやがるんですか？ \n　わしも　ドルワームへ行きますよッ！"
  },
  "93151": {
    "「えっ……？ \n　お父さん　本気で言ってるの……？": "「えっ……？ \n　お父さん　本気で言ってるの……？"
  },
  "93152": {
    "「本気に決まってますよッ！　チリやアンタらの\n　見つくろいなんて　信用できねえってんです！\n　ガラクタは　自分の目で選びますからねッ。": "「本気に決まってますよッ！　チリやアンタらの\n　見つくろいなんて　信用できねえってんです！\n　ガラクタは　自分の目で選びますからねッ。"
  },
  "93153": {
    "「ポツコン！　わしが留守の間に　ガラクタが\n　盗まれたりしないよう　しっかりと\n　戸じまりしておくようにッ！　いいですね？": "「ポツコン！　わしが留守の間に　ガラクタが\n　盗まれたりしないよう　しっかりと\n　戸じまりしておくようにッ！　いいですね？"
  },
  "93154": {
    "「は…はい～。\n　わかりました　ダストンさま！\n　気をつけて　いってらっしゃいませ。": "「は…はい～。\n　わかりました　ダストンさま！\n　気をつけて　いってらっしゃいませ。"
  },
  "93155": {
    "「……どうするんです　チリ王女？ \n　本当に　ダストン氏も\n　連れていくおつもりですか？": "「……どうするんです　チリ王女？ \n　本当に　ダストン氏も\n　連れていくおつもりですか？"
  },
  "93156": {
    "「うーん。こうなった　お父さんを\n　説得するのは　骨が折れそうだし……。\n　まあ　しょうがないかな。": "「うーん。こうなった　お父さんを\n　説得するのは　骨が折れそうだし……。\n　まあ　しょうがないかな。"
  },
  "93157": {
    "「わかりました。では　ドルワームへは\n　列車で　戻ることにしましょう。\n　じつは　特別便を手配しておきました。": "「わかりました。では　ドルワームへは\n　列車で　戻ることにしましょう。\n　じつは　特別便を手配しておきました。"
  },
  "93158": {
    "「<pc>さん。準備ができたら\n　ガタラの駅へ　向かってくれませんか？\n　そこに　特別便案内係のビノービがいます。": "「<pc>さん。準備ができたら\n　ガタラの駅へ　向かってくれませんか？\n　そこに　特別便案内係のビノービがいます。"
  },
  "93159": {
    "「我々も　すぐに後を追いますので\n　ビノービのもとで　合流しましょう。": "「我々も　すぐに後を追いますので\n　ビノービのもとで　合流しましょう。"
  },
  "93182": {
    "「ドゥラ院長が作ってくれた　高性能発信機を\n　国王様とラミザ王子にも　届けるために\n　ドルワームに　戻りたいんだけど……": "「ドゥラ院長が作ってくれた　高性能発信機を\n　国王様とラミザ王子にも　届けるために\n　ドルワームに　戻りたいんだけど……"
  },
  "93183": {
    "「ガラクタを　もらい受けるために \n　わしは　ドルワームへ出発するんですッ。\n　絶対　一緒に行ってやがりますからねッ！": "「ガラクタを　もらい受けるために \n　わしは　ドルワームへ出発するんですッ。\n　絶対　一緒に行ってやがりますからねッ！"
  },
  "93184": {
    "「……というわけなので　お父さんも一緒に\n　ドルワームに　連れていくことにするね。": "「……というわけなので　お父さんも一緒に\n　ドルワームに　連れていくことにするね。"
  },
  "93185": {
    "「わかりました。では　ドルワームへは\n　列車で　戻ることにしましょう。\n　じつは　特別便を手配しておきました。": "「わかりました。では　ドルワームへは\n　列車で　戻ることにしましょう。\n　じつは　特別便を手配しておきました。"
  },
  "93186": {
    "「<pc>さん。準備ができたら\n　ガタラの駅へ　向かってくれませんか？\n　そこに　特別便案内係のビノービがいます。": "「<pc>さん。準備ができたら\n　ガタラの駅へ　向かってくれませんか？\n　そこに　特別便案内係のビノービがいます。"
  },
  "93187": {
    "「我々も　すぐに後を追いますので\n　ビノービのもとで　合流しましょう。": "「我々も　すぐに後を追いますので\n　ビノービのもとで　合流しましょう。"
  },
  "93188": {
    "「あっ　<pc>！\n　よかった。戻ってきてくれたんだね。": "「あっ　<pc>！\n　よかった。戻ってきてくれたんだね。"
  },
  "93189": {
    "「ドゥラ院長が作ってくれた　高性能発信機を\n　国王様とラミザ王子にも　届けるために\n　ドルワームに　戻りたいんだけど……": "「ドゥラ院長が作ってくれた　高性能発信機を\n　国王様とラミザ王子にも　届けるために\n　ドルワームに　戻りたいんだけど……"
  },
  "93190": {
    "「あーんなヤツに　やられちまうなんて\n　<pc>　アンタは\n　リッパな　ポンコツですよ！": "「あーんなヤツに　やられちまうなんて\n　<pc>　アンタは\n　リッパな　ポンコツですよ！"
  },
  "93191": {
    "「とは言え　わしは　ガラクタをもらいに行くのを\n　あきらめたわけじゃねえですよ。\n　絶対　一緒に行ってやがりますからねッ！": "「とは言え　わしは　ガラクタをもらいに行くのを\n　あきらめたわけじゃねえですよ。\n　絶対　一緒に行ってやがりますからねッ！"
  },
  "93192": {
    "「……と言ってるので　お父さんも一緒に\n　ドルワームに　連れていくことにするね。": "「……と言ってるので　お父さんも一緒に\n　ドルワームに　連れていくことにするね。"
  },
  "93193": {
    "「わかりました。では　ドルワームへは\n　列車で　戻ることにしましょう。\n　同じように　特別便を手配しておきました。": "「わかりました。では　ドルワームへは\n　列車で　戻ることにしましょう。\n　同じように　特別便を手配しておきました。"
  },
  "93194": {
    "「また　列車を使って大丈夫かな。\n　もし　また襲われたりしたらって考えると\n　別ルートでの移動を　考えるべきなんじゃ……？": "「また　列車を使って大丈夫かな。\n　もし　また襲われたりしたらって考えると\n　別ルートでの移動を　考えるべきなんじゃ……？"
  },
  "93195": {
    "「いや　大丈夫でしょう。敵も\n　我々が同じルートを使うとは　思いますまい。\n　このまま　列車を使うべきです。": "「いや　大丈夫でしょう。敵も\n　我々が同じルートを使うとは　思いますまい。\n　このまま　列車を使うべきです。"
  },
  "93196": {
    "「わかったわ！\n　それじゃ　ドルワームへは\n　ドゥラ院長が　手配してくれた列車で行こう。": "「わかったわ！\n　それじゃ　ドルワームへは\n　ドゥラ院長が　手配してくれた列車で行こう。"
  },
  "93197": {
    "「<pc>さん。準備ができたら\n　ガタラの駅へ　向かってくれませんか？\n　そこに　特別便案内係のビノービがいます。": "「<pc>さん。準備ができたら\n　ガタラの駅へ　向かってくれませんか？\n　そこに　特別便案内係のビノービがいます。"
  },
  "93198": {
    "「我々も　すぐに後を追いますので\n　ビノービのもとで　合流しましょう。": "「我々も　すぐに後を追いますので\n　ビノービのもとで　合流しましょう。"
  },
  "93199": {
    "「こちらが　特別便の列車です。\n　どうぞ　中へ　お入りください！": "「こちらが　特別便の列車です。\n　どうぞ　中へ　お入りください！"
  },
  "93200": {
    "「<cs_pchero>さん　すみません。\n　少々　お待たせしてしまいましたね。": "「<cs_pchero>さん　すみません。\n　少々　お待たせしてしまいましたね。"
  },
  "93201": {
    "「さあ　私たちも　乗り込みましょう。": "「さあ　私たちも　乗り込みましょう。"
  },
  "93202": {
    "「ムキーッ　モキーッ！\n　まだ　ドルワームには着かねえんですかッ？": "「ムキーッ　モキーッ！\n　まだ　ドルワームには着かねえんですかッ？"
  },
  "93203": {
    "「……お父さんってば\n　そんな　あせらなくたって\n　ガラクタは　逃げたりしないよ。": "「……お父さんってば\n　そんな　あせらなくたって\n　ガラクタは　逃げたりしないよ。"
  },
  "93204": {
    "「これから　ドルワームのガラクタを\n　もらい受けることを考えると　ワクワクして\n　だまってなんか　いられねえですよッ！": "「これから　ドルワームのガラクタを\n　もらい受けることを考えると　ワクワクして\n　だまってなんか　いられねえですよッ！"
  },
  "93205": {
    "「ふふっ。 \n　お父さんってば……。": "「ふふっ。 \n　お父さんってば……。"
  },
  "93206": {
    "「何者だっ！？": "「何者だっ！？"
  },
  "93207": {
    "「貴様っ！　\n　さては　アストルティア中の王族を狙うという\n　不届き者だなっ！？": "「貴様っ！　\n　さては　アストルティア中の王族を狙うという\n　不届き者だなっ！？"
  },
  "93208": {
    "「……どうやら　この中にいるのは\n　間違いないようだな。": "「……どうやら　この中にいるのは\n　間違いないようだな。"
  },
  "93209": {
    "「……くっ。私は　王女を守りますので\n　<cs_pchero>さんは　ヤツの相手を\n　お願いします！！": "「……くっ。私は　王女を守りますので\n　<cs_pchero>さんは　ヤツの相手を\n　お願いします！！"
  },
  "93210": {
    "「ん……？\n　お前は　たしか……\n　ヴェリナードでも……？": "「ん……？\n　お前は　たしか……\n　ヴェリナードでも……？"
  },
  "93211": {
    "「まあ　いい……。\n　任務遂行のジャマをする者は　排除するのみ。": "「まあ　いい……。\n　任務遂行のジャマをする者は　排除するのみ。"
  },
  "93212": {
    "「ムキーッ　モキーッ！\n　まだ　ドルワームに着いてねえなんて\n　信じられねえですッ！": "「ムキーッ　モキーッ！\n　まだ　ドルワームに着いてねえなんて\n　信じられねえですッ！"
  },
  "93213": {
    "「うん……。今度こそ　無事に\n　ドルワームまで　戻れるといいんだけど……。": "「うん……。今度こそ　無事に\n　ドルワームまで　戻れるといいんだけど……。"
  },
  "93214": {
    "「なんだってっ！？": "「なんだってっ！？"
  },
  "93215": {
    "「またも　この列車を狙ってくるなんてっ！\n　次も　同じルートで来ると予測したのか！？": "「またも　この列車を狙ってくるなんてっ！\n　次も　同じルートで来ると予測したのか！？"
  },
  "93216": {
    "「……やはり　この中にいるのは\n　間違いないようだな。": "「……やはり　この中にいるのは\n　間違いないようだな。"
  },
  "93217": {
    "「……くっ。私は　王女を守りますので\n　<cs_pchero>さんは　ヤツの相手を\n　お願いします！！": "「……くっ。私は　王女を守りますので\n　<cs_pchero>さんは　ヤツの相手を\n　お願いします！！"
  },
  "93218": {
    "「任務遂行のジャマをする者は \n　何者であれ　排除するのみ。": "「任務遂行のジャマをする者は \n　何者であれ　排除するのみ。"
  },
  "93219": {
    "「チッ。 \n　だが……　狙いさえ果たせれば……。": "「チッ。 \n　だが……　狙いさえ果たせれば……。"
  },
  "93220": {
    "「この男ではなかったか……。\n　ならば……！": "「この男ではなかったか……。\n　ならば……！"
  },
  "93221": {
    "「……お前か。\n　一緒に来てもらおう。": "「……お前か。\n　一緒に来てもらおう。"
  },
  "93222": {
    "「な…なにするですかッ！？": "「な…なにするですかッ！？"
  },
  "93223": {
    "「ジャマだ！": "「ジャマだ！"
  },
  "93224": {
    "「ううっ……。": "「ううっ……。"
  },
  "93225": {
    "「ま…待てっ……！": "「ま…待てっ……！"
  },
  "93226": {
    "「……くっ。間もなく　ドルワームです。\n　駅で列車を降りたら　すぐ\n　発信機の場所を　確認しましょう。": "「……くっ。間もなく　ドルワームです。\n　駅で列車を降りたら　すぐ\n　発信機の場所を　確認しましょう。"
  },
  "93227": {
    "「あいつ……！\n　ムキーッ　ムカーッ　ですよッ！！": "「あいつ……！\n　ムキーッ　ムカーッ　ですよッ！！"
  },
  "93228": {
    "「ここは　ダラズ採掘場のダラリア砂岩遺跡です。\n　この場所は　最近になって調査が進み\n　中に　入れるようになったそうですが……": "「ここは　ダラズ採掘場のダラリア砂岩遺跡です。\n　この場所は　最近になって調査が進み\n　中に　入れるようになったそうですが……"
  },
  "93229": {
    "「なるほど。確かに　ここなら　ひと気もない。\n　身を隠すには　うってつけというわけか。": "「なるほど。確かに　ここなら　ひと気もない。\n　身を隠すには　うってつけというわけか。"
  },
  "93230": {
    "「……を　モキィーして　ムキャーするなんてッ！ \n　許せねえですッ！\n　わしは　ダラリア砂岩遺跡に行ってくるですッ！": "「……を　モキィーして　ムキャーするなんてッ！ \n　許せねえですッ！\n　わしは　ダラリア砂岩遺跡に行ってくるですッ！"
  },
  "93231": {
    "「我々も　チリ王女を救うため\n　ダラリア砂岩遺跡に向かいましょう。": "「我々も　チリ王女を救うため\n　ダラリア砂岩遺跡に向かいましょう。"
  },
  "93232": {
    "「私は　兵を率いて　追いかけます。\n　<cs_pchero>さんは　ダストン氏の後を追って\n　先に　向かっていてくれませんか？": "「私は　兵を率いて　追いかけます。\n　<cs_pchero>さんは　ダストン氏の後を追って\n　先に　向かっていてくれませんか？"
  },
  "93233": {
    "「ダラリア砂岩遺跡は　カルデア山道から\n　ダラズ採掘場に入ると　その西部にあります。\n　頼みましたよ　<cs_pchero>さん！": "「ダラリア砂岩遺跡は　カルデア山道から\n　ダラズ採掘場に入ると　その西部にあります。\n　頼みましたよ　<cs_pchero>さん！"
  },
  "93234": {
    "「<pc>さん。お待ちしておりましたよ。\n　さあ　どうぞ　こちらへ。\n　ウラード国王からの　お言葉があるそうです。": "「<pc>さん。お待ちしておりましたよ。\n　さあ　どうぞ　こちらへ。\n　ウラード国王からの　お言葉があるそうです。"
  },
  "93235": {
    "「我がドルワームの恩人　<pc>よ。\n　チリを救ってくれたこと　心から礼を言う。\n　そなたには　何度　感謝しても足りぬようじゃ。": "「我がドルワームの恩人　<pc>よ。\n　チリを救ってくれたこと　心から礼を言う。\n　そなたには　何度　感謝しても足りぬようじゃ。"
  },
  "93236": {
    "「本当に　ありがとう　<pc>！\n　また　助けられちゃったね。": "「本当に　ありがとう　<pc>！\n　また　助けられちゃったね。"
  },
  "93237": {
    "「賊が　狙っていた人物は　チリではなく\n　チリの養父ダストン氏であったことも　聞いた。\n　話を聞いた時は　おどろいたが……": "「賊が　狙っていた人物は　チリではなく\n　チリの養父ダストン氏であったことも　聞いた。\n　話を聞いた時は　おどろいたが……"
  },
  "93238": {
    "「ダストン氏には　厳重な警護をつけておる。\n　ご本人には　不満もあるようだが…… \n　後ほど　面会していってくれ。": "「ダストン氏には　厳重な警護をつけておる。\n　ご本人には　不満もあるようだが…… \n　後ほど　面会していってくれ。"
  },
  "93239": {
    "「お父さんは　自分が　重要人物扱いされることに\n　ショックを受けてるみたいだけど……\n　無事だから　心配しないでね。": "「お父さんは　自分が　重要人物扱いされることに\n　ショックを受けてるみたいだけど……\n　無事だから　心配しないでね。"
  },
  "93240": {
    "「それから……\n　ドゥラが考案した　高性能発信機で\n　その後の敵の足取りも　つかめたようじゃ。": "「それから……\n　ドゥラが考案した　高性能発信機で\n　その後の敵の足取りも　つかめたようじゃ。"
  },
  "93241": {
    "「ウラード国王。\n　それは　私から　お話ししましょう。": "「ウラード国王。\n　それは　私から　お話ししましょう。"
  },
  "93242": {
    "「チリ王女が　誘拐犯に投げつけた発信機は\n　現在　エルトナ大陸の\n　世界樹の丘にあることを　確認しました。": "「チリ王女が　誘拐犯に投げつけた発信機は\n　現在　エルトナ大陸の\n　世界樹の丘にあることを　確認しました。"
  },
  "93243": {
    "「発信機の動向を見る限り　すぐに\n　ドルワームに戻ってくることは　なさそうです。\n　ひとまず　大丈夫でしょう。とは言え……": "「発信機の動向を見る限り　すぐに\n　ドルワームに戻ってくることは　なさそうです。\n　ひとまず　大丈夫でしょう。とは言え……"
  },
  "93244": {
    "「ヤツが危険なことに　変わりありません。\n　誘拐犯の狙いは　王族では　ないようですが\n　諸王国に　この件を知らせておきます。": "「ヤツが危険なことに　変わりありません。\n　誘拐犯の狙いは　王族では　ないようですが\n　諸王国に　この件を知らせておきます。"
  },
  "93245": {
    "「<pc>は　このまま　誘拐犯の後を\n　追うんだよね？　誘拐犯をつかまえて\n　この事件を　解決するの　応援してるからね！": "「<pc>は　このまま　誘拐犯の後を\n　追うんだよね？　誘拐犯をつかまえて\n　この事件を　解決するの　応援してるからね！"
  },
  "93246": {
    "「チリや　ドルワームを救ってくださった\n　<pc>さんなら　きっと\n　成しとげてくださると信じています！": "「チリや　ドルワームを救ってくださった\n　<pc>さんなら　きっと\n　成しとげてくださると信じています！"
  },
  "93247": {
    "「何か　助けが必要な時は　いつでも\n　このドルワームを　頼るがよい。\n　そなたのためなら　協力は惜しまん。": "「何か　助けが必要な時は　いつでも\n　このドルワームを　頼るがよい。\n　そなたのためなら　協力は惜しまん。"
  },
  "93248": {
    "「それから……　ささやかじゃが\n　これは　わが娘を　危機から\n　救ってくれたほうびじゃ。受け取るがよい！": "「それから……　ささやかじゃが\n　これは　わが娘を　危機から\n　救ってくれたほうびじゃ。受け取るがよい！"
  },
  "93252": {
    "「一刻も早く　賊がつかまり\n　アストルティアの未来に　明るい太陽の光が\n　降りそそがんことを！": "「一刻も早く　賊がつかまり\n　アストルティアの未来に　明るい太陽の光が\n　降りそそがんことを！"
  },
  "93253": {
    "「……反応しない？ \n　どういうことだ……？": "「……反応しない？ \n　どういうことだ……？"
  },
  "93254": {
    "「列車の中で　この女に反応していたのは \n　間違いないはず……。\n　なぜ　急に反応しなくなった……？": "「列車の中で　この女に反応していたのは \n　間違いないはず……。\n　なぜ　急に反応しなくなった……？"
  },
  "93255": {
    "「誰だっ！？": "「誰だっ！？"
  },
  "93256": {
    "「ぜーっ　ぜーっ……！ \n　モキィーして　ムキャーするなんてッ\n　許せねえですッ！！": "「ぜーっ　ぜーっ……！ \n　モキィーして　ムキャーするなんてッ\n　許せねえですッ！！"
  },
  "93257": {
    "「そいつは　とーっても\n　役に立たねえ娘なんですッ！\n　だから　返してもらいに来たですよッ！！": "「そいつは　とーっても\n　役に立たねえ娘なんですッ！\n　だから　返してもらいに来たですよッ！！"
  },
  "93258": {
    "「何を　わけのわからぬことを……。": "「何を　わけのわからぬことを……。"
  },
  "93259": {
    "「ん……？ \n　なぜ　急に反応しだした……？": "「ん……？ \n　なぜ　急に反応しだした……？"
  },
  "93260": {
    "「まだ　これからだというのに　不調か……。 \n　……このクズが！！": "「まだ　これからだというのに　不調か……。 \n　……このクズが！！"
  },
  "93261": {
    "「……クズ！？": "「……クズ！？"
  },
  "93262": {
    "「そのヘビは　ポンコツなんですね。\n　ポンコツヘビを　わしにも見せてくだせえ。\n　チリと一緒に　連れかえってやりますよッ！": "「そのヘビは　ポンコツなんですね。\n　ポンコツヘビを　わしにも見せてくだせえ。\n　チリと一緒に　連れかえってやりますよッ！"
  },
  "93263": {
    "「や…やめろ……！": "「や…やめろ……！"
  },
  "93264": {
    "「そうか……　そうだったのか。\n　……お前こそが　器だったのだな！！": "「そうか……　そうだったのか。\n　……お前こそが　器だったのだな！！"
  },
  "93265": {
    "「器は　いただいていく！": "「器は　いただいていく！"
  },
  "93268": {
    "「……一緒に来い。": "「……一緒に来い。"
  },
  "93269": {
    "「ムキィーッ！　モキャーッ！！": "「ムキィーッ！　モキャーッ！！"
  },
  "93270": {
    "「……何度　むらがってこようと\n　コバエには　何もできはしない。\n　器は　いただいていく！": "「……何度　むらがってこようと\n　コバエには　何もできはしない。\n　器は　いただいていく！"
  },
  "93271": {
    "「……ほう。\n　黄牛鬼までも　討ちやぶったか……。": "「……ほう。\n　黄牛鬼までも　討ちやぶったか……。"
  },
  "93272": {
    "「<cs_pchero>さん！　お待たせしました！！": "「<cs_pchero>さん！　お待たせしました！！"
  },
  "93273": {
    "「……チッ　面倒だな。": "「……チッ　面倒だな。"
  },
  "93274": {
    "「チリ王女！！\n　おケガは　ありませんかっ！？": "「チリ王女！！\n　おケガは　ありませんかっ！？"
  },
  "93275": {
    "「うん　大丈夫だよ。\n　少しの間　気を失ってただけ。": "「うん　大丈夫だよ。\n　少しの間　気を失ってただけ。"
  },
  "93276": {
    "「本当は　途中から目が覚めていたんだけど……\n　何か　誘拐犯の情報をつかめないかと思って\n　気絶したフリを　続けていたの。": "「本当は　途中から目が覚めていたんだけど……\n　何か　誘拐犯の情報をつかめないかと思って\n　気絶したフリを　続けていたの。"
  },
  "93277": {
    "「でも　ダメ。\n　さすがに　シッポをつかませるような情報は\n　得られなかったわ……。": "「でも　ダメ。\n　さすがに　シッポをつかませるような情報は\n　得られなかったわ……。"
  },
  "93278": {
    "「それで　とっさに　発信機を投げつけることを \n　思いついたんだけど\n　なんとか　うまくいって　よかったわ！": "「それで　とっさに　発信機を投げつけることを \n　思いついたんだけど\n　なんとか　うまくいって　よかったわ！"
  },
  "93279": {
    "「なるほど。急に　チリ王女が\n　起き上がった時は　おどろきましたが……\n　これで　ヤツの足取りを追うことができます！": "「なるほど。急に　チリ王女が\n　起き上がった時は　おどろきましたが……\n　これで　ヤツの足取りを追うことができます！"
  },
  "93280": {
    "「フン！\n　わしは　アンタのこと\n　そんな優秀に育てた覚えは　ねえですよッ！": "「フン！\n　わしは　アンタのこと\n　そんな優秀に育てた覚えは　ねえですよッ！"
  },
  "93281": {
    "「それに比べて　アンタってヤツは…… \n　元ポツコン２号が　ぜーんぶ片付けちまった後に\n　のこのこ　兵を率いてやってくるなんて……": "「それに比べて　アンタってヤツは…… \n　元ポツコン２号が　ぜーんぶ片付けちまった後に\n　のこのこ　兵を率いてやってくるなんて……"
  },
  "93282": {
    "「どんな優秀なヤツかと　思ってましたが \n　アンタも　院長とは名ばかりの\n　リッパなポンコツだったんですねえ！": "「どんな優秀なヤツかと　思ってましたが \n　アンタも　院長とは名ばかりの\n　リッパなポンコツだったんですねえ！"
  },
  "93283": {
    "「なん……！？ \n　わ…私が　ポン…コツ……？": "「なん……！？ \n　わ…私が　ポン…コツ……？"
  },
  "93284": {
    "「ま　まあ。それは　ともかく…… \n　誘拐犯の　足取りのほかに\n　もうひとつ　わかったことがあるわ！": "「ま　まあ。それは　ともかく…… \n　誘拐犯の　足取りのほかに\n　もうひとつ　わかったことがあるわ！"
  },
  "93285": {
    "「それは……　敵の狙いは \n　私ではなく　お父さんだったということ。\n　誘拐犯は　王族を狙っているわけではない……？": "「それは……　敵の狙いは \n　私ではなく　お父さんだったということ。\n　誘拐犯は　王族を狙っているわけではない……？"
  },
  "93286": {
    "「もう！　ドゥラ院長ったら！\n　いつまで　ショックを受けてるの！？\n　このことを　国王様に急いで知らせましょう。": "「もう！　ドゥラ院長ったら！\n　いつまで　ショックを受けてるの！？\n　このことを　国王様に急いで知らせましょう。"
  },
  "93287": {
    "「……ハッ！？　そうですね。": "「……ハッ！？　そうですね。"
  },
  "93288": {
    "「今　この場で　もっとも重要と思われる人物……": "「今　この場で　もっとも重要と思われる人物……"
  },
  "93289": {
    "「……へ？　へ？": "「……へ？　へ？"
  },
  "93290": {
    "「ダストン氏を　厳重に保護せよ！": "「ダストン氏を　厳重に保護せよ！"
  },
  "93291": {
    "「や…やめてくだせぇ～ッ……！": "「や…やめてくだせぇ～ッ……！"
  },
  "93292": {
    "「我々は　いったん　ドルワームに戻ります。 \n　<cs_pchero>さんも　来てください。\n　国王と共に　今後の検討をしたいと思います。": "「我々は　いったん　ドルワームに戻ります。 \n　<cs_pchero>さんも　来てください。\n　国王と共に　今後の検討をしたいと思います。"
  },
  "93293": {
    "「それじゃ　<cs_pchero>！ \n　ドルワーム水晶宮の玉座の間に　すぐ来てね。": "「それじゃ　<cs_pchero>！ \n　ドルワーム水晶宮の玉座の間に　すぐ来てね。"
  },
  "93294": {
    "「ムキャーッ！　モキィーッ！！\n　今すぐ！　わしを！　ここから出すですッ！！": "「ムキャーッ！　モキィーッ！！\n　今すぐ！　わしを！　ここから出すですッ！！"
  },
  "93295": {
    "「ぜーっ　ぜーっ……。": "「ぜーっ　ぜーっ……。"
  },
  "93296": {
    "「いいかげん　あきらめて\n　おとなしくしてください。": "「いいかげん　あきらめて\n　おとなしくしてください。"
  },
  "93297": {
    "「敵の目的は　わかりませんが\n　今のあなたは　重要人物として狙われる身。\n　少しは　自覚を持っていただかないと困ります。": "「敵の目的は　わかりませんが\n　今のあなたは　重要人物として狙われる身。\n　少しは　自覚を持っていただかないと困ります。"
  },
  "93298": {
    "「ひ…ひいいいい……。\n　じゅ　重要とか　言わねえでくだせえッ……！！\n　わしは　そんな役立ちそうなものゴメンですッ！": "「ひ…ひいいいい……。\n　じゅ　重要とか　言わねえでくだせえッ……！！\n　わしは　そんな役立ちそうなものゴメンですッ！"
  },
  "93299": {
    "「はあ…………。 \n　何度聞いても　あなたの価値観には　\n　おどろきを　禁じえませんよ……。": "「はあ…………。 \n　何度聞いても　あなたの価値観には　\n　おどろきを　禁じえませんよ……。"
  },
  "93300": {
    "「ムキャーッ！　モキィーッ！！": "「ムキャーッ！　モキィーッ！！"
  },
  "93301": {
    "「<pc>　来てくれて　ありがとう。\n　さわがしくて　ごめんね？\n　お父さんは　ご覧の通りで……。": "「<pc>　来てくれて　ありがとう。\n　さわがしくて　ごめんね？\n　お父さんは　ご覧の通りで……。"
  },
  "93302": {
    "「でも　お父さんが　落ち着くまでは \n　しばらく　私も　ここにいるつもりだし\n　心配しないで　あなたの目的を追って。": "「でも　お父さんが　落ち着くまでは \n　しばらく　私も　ここにいるつもりだし\n　心配しないで　あなたの目的を追って。"
  },
  "93303": {
    "「私が　誘拐犯に投げた発信機は\n　エルトナ大陸の世界樹の丘に　あるそうね。\n　この事件が早く解決することを　願ってるわ！": "「私が　誘拐犯に投げた発信機は\n　エルトナ大陸の世界樹の丘に　あるそうね。\n　この事件が早く解決することを　願ってるわ！"
  },
  "93304": {
    "「ムキャーッ！　モキィーッ！！\n　もう！　わしは！　こんな生活イヤなんですッ！": "「ムキャーッ！　モキィーッ！！\n　もう！　わしは！　こんな生活イヤなんですッ！"
  },
  "93305": {
    "「ぜーっ　ぜーっ……。": "「ぜーっ　ぜーっ……。"
  },
  "93306": {
    "「あなたも　こりないですね……。\n　いいかげんに　してください……。": "「あなたも　こりないですね……。\n　いいかげんに　してください……。"
  },
  "93307": {
    "「多少の不自由があるとは言え \n　これだけ　丁重に　もてなされ……\n　いったい　なんの不満があると言うのですか？": "「多少の不自由があるとは言え \n　これだけ　丁重に　もてなされ……\n　いったい　なんの不満があると言うのですか？"
  },
  "93308": {
    "「ひ…ひいいいい……。\n　て　丁重とか　言わねえでくだせえッ……！！\n　わしは　そんな扱いされるのはゴメンですッ！": "「ひ…ひいいいい……。\n　て　丁重とか　言わねえでくだせえッ……！！\n　わしは　そんな扱いされるのはゴメンですッ！"
  },
  "93309": {
    "「とにかく……　もう二度と　ドルボードを使って \n　逃げ出そうとなんて　しないでください。\n　いいですねっ！？": "「とにかく……　もう二度と　ドルボードを使って \n　逃げ出そうとなんて　しないでください。\n　いいですねっ！？"
  },
  "93310": {
    "「ムキャーッ！　モキィーッ！！": "「ムキャーッ！　モキィーッ！！"
  },
  "93311": {
    "「ああっ　<pc>。来てくれたんだ。\n　さわがしくて　ごめんね？\n　お父さんは　相変わらずで……。": "「ああっ　<pc>。来てくれたんだ。\n　さわがしくて　ごめんね？\n　お父さんは　相変わらずで……。"
  },
  "93312": {
    "「早く　事件が解決して\n　お父さんが　自由になれるといいんだけど……。": "「早く　事件が解決して\n　お父さんが　自由になれるといいんだけど……。"
  },
  "93313": {
    "「<pc>は　今も事件を追ってるんだよね？\n　<pc>が　事件を解決して\n　この世界に平穏が戻ることを　願ってるわ！": "「<pc>は　今も事件を追ってるんだよね？\n　<pc>が　事件を解決して\n　この世界に平穏が戻ることを　願ってるわ！"
  },
  "103851": {
    "「私としたことが　取り乱すとは　とんだ失礼を。\n　では　気を取り直して……　コホン。": "「私としたことが　取り乱すとは　とんだ失礼を。\n　では　気を取り直して……　コホン。"
  },
  "116709": {
    "「し…信じられないな。\n　この人が　チリ王女の育ての親だと言うのか！？": "「し…信じられないな。\n　この人が　チリ王女の育ての親だと言うのか！？"
  },
  "116710": {
    "「ぐ…ぷぷぷぷぷ……。": "「ぐ…ぷぷぷぷぷ……。"
  },
  "116711": {
    "「……なんだと！？": "「……なんだと！？"
  },
  "117870": {
    "「これで　貴様には　何もできまい。": "「これで　貴様には　何もできまい。"
  },
  "117871": {
    "「また　貴様か。\n　わずらわしい　コバエのような奴め！！": "「また　貴様か。\n　わずらわしい　コバエのような奴め！！"
  },
  "119099": {
    "<pc>は　チリたちと共に\nダストンが　警護されているという\nドルワーム王立研究院の院長室に　向かった。": "<pc>は　チリたちと共に\nダストンが　警護されているという\nドルワーム王立研究院の院長室に　向かった。"
  }
}
