{
  "323811": {
    "「あはは！　何度見ても\n　あたし　すっごい　いい笑顔！\n　<pc>に　撮ってもらったからかなぁ？": "「あはは！　何度見ても\n　あたし　すっごい　いい笑顔！\n　<pc>に　撮ってもらったからかなぁ？"
  },
  "323812": {
    "「バーベキューも　おいしかったな～。\n　鉄板で焼く　お肉が　ジューシーで！\n　いっぱい　食べちゃったよ。": "「バーベキューも　おいしかったな～。\n　鉄板で焼く　お肉が　ジューシーで！\n　いっぱい　食べちゃったよ。"
  },
  "323813": {
    "「それでさ……お肉　おいしいから\n　やっぱり　ラキにも\n　食べてほしいなーって　思っちゃって。": "「それでさ……お肉　おいしいから\n　やっぱり　ラキにも\n　食べてほしいなーって　思っちゃって。"
  },
  "323814": {
    "「おみやげに　お肉ぎっしりサンドイッチを\n　買って　帰ったんだよね。\n　えと……どうだった？　ラキ。": "「おみやげに　お肉ぎっしりサンドイッチを\n　買って　帰ったんだよね。\n　えと……どうだった？　ラキ。"
  },
  "323815": {
    "「……ポルテが　しつこいから　食べたけど\n　ラキには　よく　わからなかった。\n　味とか　おいしいとか……。": "「……ポルテが　しつこいから　食べたけど\n　ラキには　よく　わからなかった。\n　味とか　おいしいとか……。"
  },
  "323816": {
    "「そっか……ラキは　ごはん食べないし\n　味覚とか　わかんなくて　トーゼンなのかも。": "「そっか……ラキは　ごはん食べないし\n　味覚とか　わかんなくて　トーゼンなのかも。"
  },
  "323817": {
    "「でもさ　ラキ。味は　わからなくても\n　感じたことはあるんじゃない？\n　おクチが　しあわせ～とか　いい感じ～とか。": "「でもさ　ラキ。味は　わからなくても\n　感じたことはあるんじゃない？\n　おクチが　しあわせ～とか　いい感じ～とか。"
  },
  "323818": {
    "「感じたこと……。": "「感じたこと……。"
  },
  "323819": {
    "「肉をかむと……汁が出てくる。\n　あと……クチのまわりが　ベトベトになる。": "「肉をかむと……汁が出てくる。\n　あと……クチのまわりが　ベトベトになる。"
  },
  "323820": {
    "「逆に　ザンシンな　食レポ……！": "「逆に　ザンシンな　食レポ……！"
  },
  "323821": {
    "「でも……悪くなかった。と　思う……。": "「でも……悪くなかった。と　思う……。"
  },
  "323822": {
    "「……えへへー。\n　また　おみやげ　買ってくるからね！": "「……えへへー。\n　また　おみやげ　買ってくるからね！"
  }
}
