{
  "1": {
    "「<cs_pchero>　任務　ご苦労。|　近くに　別の任務が　あったので|　貴公の様子を　見にきたのだ。": "<cs_pchero> Mission . I had another|mission nearby, so I thought I'd check in on|you."
  },
  "2": {
    "「なるほど……。ニシキ殿の言うとおり|　あれは　ウェナ諸島内だけに棲息している|　タップペンギーという名の魔物だ。": "I see. You're right. It's a tapalpaengi, a|species found only in the Wena Islands."
  },
  "3": {
    "「これは　貴公の任務だからな。|　私の手を借りずに　討伐してみせてくれ。": "This is your mission. You will take them|down without my help."
  },
  "4": {
    "「グルル……？　グルルルルゥ！！": "Grrr...?"
  },
  "5": {
    "「テキスト削除": "text deletion"
  },
  "6": {
    "「<cs_pchero>　任務　ご苦労。|　だが　あの程度の魔物に　手こずるようでは|　先が　思いやられるぞ。": "<cs_pchero> Mission . But if we can't|handle a monster of that caliber, I don't|know what we're going to do."
  },
  "7": {
    "「これは　貴公の任務だ。|　私の手を借りようなどと　思うな。": "This is your... You don't need my help."
  },
  "8": {
    "「グルゥ……？　グルルルァァ！！": "Gru...? Grrrrrrrrrrrrrrrrr!"
  },
  "9": {
    "「テキスト削除": "text deletion"
  },
  "10": {
    "「貴公の手並みは　見せてもらった。|　戦いのウデも　なかなかだな。": "I'll show you how you do it. But you're not|a great fighter."
  },
  "11": {
    "「私は　このエルトナ大陸でも|　多くの魔物討伐任務を　果たしてきたが|　タップペンギーを　見たことはなかった。": "I've been on many demon-killing missions|here on Eltona, but I've never seen a Tap|Pengy."
  },
  "12": {
    "「なぜ　この大陸に現れたのか　気になる。|　衛士団ならば　この魔物のことを|　何か　知っているかもしれないな……。": "I wonder why it appeared on this continent.|Maybe the Guardians know something about|this monster."
  },
  "13": {
    "「貴公は　カミハルムイ国へ戻り|　ニシキ殿に　依頼の完了を報告せよ。|　私は　ヴェリナードへ戻っている。": "You will return to Kamikhalmuy and inform|Lord Nyiskiyah of the completion of his|request. I will return to Verinado."
  },
  "14": {
    "「遅いぞ　衛士団。なぜ　すぐに来ないのだ。": "You're late . Why didn't you come sooner?"
  },
  "15": {
    "「ガハハハッ。そんなに　待たせたか？|　そっちの都合で　呼びつけたんだ。|　すこしは　ガマンしてくれ。": "Gaha. Did I make you wait that long? You|called me for your own reasons. You've got|to be a little patient."
  },
  "16": {
    "「……貴公らに　聞きたいことがある。|　タップペンギーという　魔物について|　教えてもらいたい。": "... I have a question for you. Tell us about|the demon Tappenghi."
  },
  "17": {
    "「教えるのはいいが……。|　その程度の　魔物のことならば|　ウェナ諸島を守る衛士にとって　当然の知識だ。": "I'm happy to teach you. But that's about as|much demon knowledge as the guards who|protect the Wena Islands have to offer."
  },
  "18": {
    "「そんなことも知らんとは|　魔法戦士団は　足もとが|　おろそかに　なってるんじゃないのか？": "You don't know that? Are you not following|the footsteps of the Mage Clan?"
  },
  "19": {
    "「我が魔法戦士団は　世界を舞台にしている。　|　貴公たちとは　守るべきものの大きさも|　責任の重さも　ちがうと知りたまえ。": "Our Mage Legion takes the world by storm. We|know that we have different priorities and|responsibilities than you."
  },
  "20": {
    "「はっ！　聞いて　あきれるぜ！|　オレたちが　ウェナ諸島を守っているから|　魔法戦士団は　外に出ていけるんだろうが！": "Ha! I'm so sick of this! We're the ones who|protect the Wena Islands so the Warlocks can|get out!"
  },
  "21": {
    "「ザイナー殿。衛士団の意見は　求めていない。|　魔物のことを　教える気はあるのか？": "XY. I need your opinion on the Guard. Are|you willing to teach them about demons?"
  },
  "22": {
    "「お前の担当地域の　魔物だったな。|　教えてやれ　ノーラン。": "It's a demon in your area. Tell him, No."
  },
  "23": {
    "「タップペンギーは　このウェナ諸島で|　独特の生態を持って　棲息している魔物です。": "The Tap Penguins are the unique ecological|inhabitants of the Wena Islands."
  },
  "24": {
    "「その魔物が　ウェナ諸島の外に|　棲みつくようなことは　あるのか？": "Is there any chance that these demons will|ever make their home outside of the Wena|Islands?"
  },
  "25": {
    "「それは　ありえません。|　気候の変化に弱いですし　エサもないでしょう。": "That's impossible. It's vulnerable to|climate change and has no food."
  },
  "26": {
    "「なるほど　普通でないことは　わかった。|　それだけ聞ければ　後は　こちらで対応する。|　貴公らは　任務に戻るがいい。": "I see. I know it's not normal. If that's all|you've got to say, we'll take it from here.|You're going back to work."
  },
  "27": {
    "「呼びつけておいて　それだけか……。|　帰るぞ　ノーラン！": "You called me up here and that's it? Let's|go home, Nolan!"
  },
  "28": {
    "「……ノーラン。": "...ノ."
  },
  "29": {
    "「いつまで　衛士などに　甘んじている。|　我ら　魔法戦士団の一員となる決心は|　まだ　つかんのか？": "How long will you be a guard? Have you made|up your mind yet to become a member of our|order?"
  },
  "30": {
    "「私は…………|　魔法戦士には　なりません。": "I'm... I don't want to be a Mage."
  },
  "31": {
    "「待たせて　すまなかった　<pc>。|　貴公の任務は　完了している。": "I'm sorry you had to wait so long,|<pc>, but your mission is|complete."
  },
  "32": {
    "「では　報酬を受け取ってくれ。|　貴公には　これが似合う魔法戦士に|　なってほしいものだ。": "Then you'll get your reward. I want you to|become the kind of warrior who looks good in|this."
  },
  "33": {
    "「では　報酬を受け取ってくれ。": "Then you get paid."
  },
  "34": {
    "「タップペンギーの件については|　こちらで　調べておこう。|　結果によっては　貴公の協力も必要となる。": "I'll look into the Tap Penguins. Depending|on the results, we may need your help."
  },
  "35": {
    "「調査には　時間を要するかもしれない。|　それまで　貴公は　独自に修行を積み|　魔法戦士となって　また　ここに来るように。": "It may take some time to find out. Until|then, you will train on your own and come|back here as a warrior."
  }
}