{
  "15964": {
    "「ただいま　戻りましたなのだー！": "I'm back! I'm back!"
  },
  "15965": {
    "「遠くまで　ご苦労だったな　ズーボー。\n　あんなに大きなツボを　ひとりで\n　守りきるのは　大変だったろう？": "You've come a long way, Zubo. Must have been\nhard to defend such a big pot all by yourself,\nhuh?"
  },
  "15966": {
    "「問題なしなのだ！\n　届けた先で待っていた　おばあさんが　とっても\n　よろこんでくれたのだ！　だから　平気なのだ！": "No problem! The old lady who was waiting for\nme when I delivered it was so happy! So I'm\nfine!"
  },
  "15967": {
    "「あのツボは　依頼人の老婦人にとって\n　かけがえのない　思い出の品だった。": "That pot was an irreplaceable Memory Jar for\nmy client, an old lady."
  },
  "15968": {
    "「多忙な　オレたちに代わって\n　ツボを届けてくれたこと　感謝する。\n　少ないが　今回の報酬だ。受け取ってくれ！": "Thank you for delivering the pot on behalf of\nus busy people. It's not much, but it's our\nreward. Take it!"
  },
  "15969": {
    "「どういたしましてなのだ！\n　ふうっ……　いい汗　かいたのだ。": "You're welcome! Phew... I worked up a good\nsweat."
  },
  "15970": {
    "「いやあ　すばらしい！\n　やっぱり　雇われパラディンさんは　ちがうね！": "Oh, wonderful! You're a paladin for hire,\nafter all!"
  },
  "15971": {
    "「あんな　芸術品でもない　ただの安物のツボを\n　一生懸命　護衛するなんて……\n　ボクには　とても　マネできないよ。": "I can't imagine myself working so hard to\nprotect a cheap, non-artistic pot like that."
  },
  "15972": {
    "「ぬぬぬ！　バカにされているのだ！\n　オイラは　ともかく　おばあさんのツボまで\n　バカにされるのは　許せないのだ！": "Noooooo! They are making fun of me! I, for\none, will not allow my grandmother's pot to be\nmade fun of!"
  },
  "15973": {
    "「大切なものを守るのは　パラディンとして\n　あたりまえの　仕事なのだ！": "It is our job as paladins to protect what we\nhold dear!"
  },
  "15974": {
    "「しかしねぇ……": "But hey..."
  },
  "15975": {
    "「その辺にしておけ　ディヒド。": "Leave it at that, Dihido."
  },
  "15976": {
    "「オレたちが　国務に集中できるのは\n　雇われパラディンたちの　協力があってこそ！\n　決して　そのことを忘れるな！": "It is only with the help of the hired paladins\nthat we can concentrate on the affairs of\nstate! Never forget that!"
  },
  "15977": {
    "「ズーボー。\n　これからも　助けを求める者たちに\n　チカラを貸す　パラディンであってくれ！": "Zubo. Be the paladin who will continue to help\nthose who need help!"
  },
  "15978": {
    "「もちろんなのだ！": "Of course!"
  },
  "15979": {
    "「うむ　いい返事だ。": "Mm, good answer."
  },
  "15980": {
    "「やったなのだ！\n　仕事の仲間が　できたのだ！\n　オイラは　ズーボー。よろしくなのだ！": "We did it! I have a business companion! I'm\nZubo. Nice to meet you!"
  },
  "15981": {
    "「では　<pc>が　パラディンに転職し\n　時をおいて　レベル３０以上になった頃\n　また来るがいい。": "Then <pc> will change his job to\npaladin, wait a while, and come back when he\nis level 30+."
  },
  "15982": {
    "「楽しみなのだ！\n　オイラ　<pc>が　来てないか\n　毎日　ここへ見にくるのだ！": "I can't wait! I come here every day to see if\n<pc> is here!"
  },
  "15983": {
    "「パラディンは　仲間を守れる　職業なのだ！\n　<pc>も　楽しんで　修行するのだ。\n　また　会える日を　楽しみにしているのだ！": "A paladin is a profession where one can\nprotect one's companions! Enjoy your training,\n<pc>. I look forward to seeing you\n<br>\nagain!"
  },
  "27078": {
    "「……そうだ　紹介しよう。\n　先ほど　パラディンに　転職できるように\n　なったばかりの　<pc>だ。": "...Yes, let me introduce you. <pc>,\nwho just recently became able to convert to a\npaladin."
  }
}
